Metadata-Version: 2.1
Name: brel-xbrl
Version: 0.8.2a1
Summary: An XBRL parser for Python
Home-page: https://github.com/BrelLibrary/brel/
Author: PapediPoo, shreymittal1000, ghislainfourny
Requires-Python: >=3.10
License-File: LICENSE
Requires-Dist: certifi==2023.11.17
Requires-Dist: charset-normalizer==3.3.2
Requires-Dist: idna==3.6
Requires-Dist: lxml==5.1.0
Requires-Dist: markdown-it-py==3.0.0
Requires-Dist: mdurl==0.1.2
Requires-Dist: pandas==2.2.1
Requires-Dist: prettytable==3.9.0
Requires-Dist: py4j==0.10.9.7
Requires-Dist: Pygments==2.17.2
Requires-Dist: pyspark==3.5.1
Requires-Dist: python-dateutil==2.8.2
Requires-Dist: requests==2.31.0
Requires-Dist: rich==13.7.1
Requires-Dist: six==1.16.0
Requires-Dist: urllib3==2.1.0
Requires-Dist: wcwidth==0.2.13
Provides-Extra: test
Requires-Dist: black==23.12.1; extra == "test"
Requires-Dist: certifi==2023.11.17; extra == "test"
Requires-Dist: charset-normalizer==3.3.2; extra == "test"
Requires-Dist: click==8.1.7; extra == "test"
Requires-Dist: coverage==7.4.3; extra == "test"
Requires-Dist: databind.core==4.4.2; extra == "test"
Requires-Dist: databind.json==4.4.2; extra == "test"
Requires-Dist: Deprecated==1.2.14; extra == "test"
Requires-Dist: docspec==2.2.1; extra == "test"
Requires-Dist: docspec-python==2.2.1; extra == "test"
Requires-Dist: docstring_parser==0.11; extra == "test"
Requires-Dist: ghp-import==2.1.0; extra == "test"
Requires-Dist: graphviz==0.20.1; extra == "test"
Requires-Dist: idna==3.6; extra == "test"
Requires-Dist: importlib-metadata==7.0.1; extra == "test"
Requires-Dist: iniconfig==2.0.0; extra == "test"
Requires-Dist: Jinja2==3.1.3; extra == "test"
Requires-Dist: lxml==5.1.0; extra == "test"
Requires-Dist: Markdown==3.5.2; extra == "test"
Requires-Dist: markdown-it-py==3.0.0; extra == "test"
Requires-Dist: MarkupSafe==2.1.5; extra == "test"
Requires-Dist: mdurl==0.1.2; extra == "test"
Requires-Dist: mergedeep==1.3.4; extra == "test"
Requires-Dist: mkdocs==1.5.3; extra == "test"
Requires-Dist: mypy==1.8.0; extra == "test"
Requires-Dist: mypy-extensions==1.0.0; extra == "test"
Requires-Dist: nr-date==2.1.0; extra == "test"
Requires-Dist: nr-stream==1.1.5; extra == "test"
Requires-Dist: nr.util==0.8.12; extra == "test"
Requires-Dist: numpy==1.26.4; extra == "test"
Requires-Dist: packaging==23.2; extra == "test"
Requires-Dist: pandas==2.2.1; extra == "test"
Requires-Dist: pathspec==0.12.1; extra == "test"
Requires-Dist: platformdirs==4.2.0; extra == "test"
Requires-Dist: pluggy==1.4.0; extra == "test"
Requires-Dist: prettytable==3.9.0; extra == "test"
Requires-Dist: py4j==0.10.9.7; extra == "test"
Requires-Dist: pydoc-markdown==4.8.2; extra == "test"
Requires-Dist: Pygments==2.17.2; extra == "test"
Requires-Dist: pyspark==3.5.1; extra == "test"
Requires-Dist: pytest==8.0.2; extra == "test"
Requires-Dist: pytest-cov==4.1.0; extra == "test"
Requires-Dist: python-dateutil==2.8.2; extra == "test"
Requires-Dist: pytz==2024.1; extra == "test"
Requires-Dist: PyYAML==6.0.1; extra == "test"
Requires-Dist: pyyaml_env_tag==0.1; extra == "test"
Requires-Dist: requests==2.31.0; extra == "test"
Requires-Dist: rich==13.7.1; extra == "test"
Requires-Dist: six==1.16.0; extra == "test"
Requires-Dist: tomli==2.0.1; extra == "test"
Requires-Dist: tomli_w==1.0.0; extra == "test"
Requires-Dist: typeapi==2.1.2; extra == "test"
Requires-Dist: types-python-dateutil==2.8.19.20240106; extra == "test"
Requires-Dist: types-requests==2.31.0.20240218; extra == "test"
Requires-Dist: typing_extensions==4.6.3; extra == "test"
Requires-Dist: tzdata==2024.1; extra == "test"
Requires-Dist: urllib3==2.1.0; extra == "test"
Requires-Dist: watchdog==4.0.0; extra == "test"
Requires-Dist: wcwidth==0.2.13; extra == "test"
Requires-Dist: wrapt==1.16.0; extra == "test"
Requires-Dist: yapf==0.40.2; extra == "test"
Requires-Dist: zipp==3.17.0; extra == "test"
